{"id":"8jtepud2k2y877ns99o5ny8","title":"AHK","desc":"","updated":1664244654128,"created":1663736355962,"custom":{},"fname":"Projects.Automation.AHK","type":"note","vault":{"fsPath":".","selfContained":true,"name":"Dendron-1"},"contentHash":"52b06661bbf4e4a1518f16af6ce81aff","links":[{"from":{"fname":"Projects.Automation","id":"7oln5eqmmokvnyevsaj1sf5","vaultName":"Dendron-1"},"type":"backlink","position":{"start":{"line":9,"column":3,"offset":181},"end":{"line":9,"column":34,"offset":212},"indent":[]},"value":"Projects.Automation.AHK"}],"anchors":{"dendron-macros":{"type":"header","text":"Dendron macros:","value":"dendron-macros","line":9,"column":0,"depth":1},"note-creation-helper":{"type":"header","text":"Note creation helper","value":"note-creation-helper","line":11,"column":0,"depth":2}},"children":["et0i96heteukv7m12mwdwbw","sgbh78h20hoyi77beo40tbw","g9zv14g45j01ktu4q8wlg0d","lwmj6wvx0mm4s24hvp06k04"],"parent":"7oln5eqmmokvnyevsaj1sf5","data":{}}
