{"id":"iiarz11zzpdnj4y6axlrjra","title":"Solidworks","desc":"","updated":1665953453053,"created":1665947610322,"tags":"Project","filesaveloc":"","priority":null,"startDate":"TODO: date to start","launchDate":"TODO: when project ends","custom":{"filesaveloc":"","priority":null,"startDate":"TODO: date to start","launchDate":"TODO: when project ends"},"fname":"Projects.Automation.Solidworks","type":"note","vault":{"fsPath":".","selfContained":true,"name":"Dendron-1"},"contentHash":"e5d48c5ad08a7e7eb2d7c2a137b5fcc3","links":[{"type":"frontmatterTag","from":{"fname":"Projects.Automation.Solidworks","id":"iiarz11zzpdnj4y6axlrjra","vaultName":"Dendron-1"},"value":"tags.Project","alias":"Project","xvault":false,"to":{"fname":"tags.Project"}}],"anchors":{"title":{"type":"header","text":"Title","value":"title","line":14,"column":0,"depth":2},"description":{"type":"header","text":"Description","value":"description","line":17,"column":0,"depth":2},"goal":{"type":"header","text":"Goal","value":"goal","line":42,"column":0,"depth":2},"context":{"type":"header","text":"Context","value":"context","line":50,"column":0,"depth":2},"success-criteria":{"type":"header","text":"Success Criteria","value":"success-criteria","line":53,"column":0,"depth":2},"sub-projects":{"type":"header","text":"Sub Projects","value":"sub-projects","line":56,"column":0,"depth":2},"log":{"type":"header","text":"Log","value":"log","line":59,"column":0,"depth":2},"outputs":{"type":"header","text":"Outputs","value":"outputs","line":62,"column":0,"depth":2},"tasks":{"type":"header","text":"Tasks","value":"tasks","line":67,"column":0,"depth":2},"notes":{"type":"header","text":"Notes","value":"notes","line":70,"column":0,"depth":2},"ideas":{"type":"header","text":"Ideas","value":"ideas","line":73,"column":0,"depth":2}},"children":["73dm0w0g63bhgxgfli2ugjf"],"parent":"7oln5eqmmokvnyevsaj1sf5","data":{}}
